opentelemetry/semconv_ai/__init__.py
opentelemetry/semconv_ai/utils.py
opentelemetry/semconv_ai/version.py
opentelemetry_semantic_conventions_ai-0.4.10.dist-info/METADATA
opentelemetry_semantic_conventions_ai-0.4.10.dist-info/WHEEL
opentelemetry_semantic_conventions_ai-0.4.10.dist-info/RECORD
