Metadata-Version: 2.1
Name: opentelemetry-semantic-conventions-ai
Version: 0.4.10
Summary: OpenTelemetry Semantic Conventions Extension for Large Language Models
License: Apache-2.0
Author: Gal Kleinman
Author-email: gal@traceloop.com
Requires-Python: >=3.9,<4
Classifier: License :: OSI Approved :: Apache Software License
Classifier: Programming Language :: Python :: 3
Classifier: Programming Language :: Python :: 3.9
Classifier: Programming Language :: Python :: 3.10
Classifier: Programming Language :: Python :: 3.11
Classifier: Programming Language :: Python :: 3.12
